riverwm_utils/__init__.py
riverwm_utils/river-control-unstable-v1.xml
riverwm_utils/river-status-unstable-v1.xml
riverwm_utils/riverwm_utils.py
riverwm_utils/wayland.xml
riverwm_utils-0.0.10.dist-info/LICENSE
riverwm_utils-0.0.10.dist-info/METADATA
riverwm_utils-0.0.10.dist-info/WHEEL
riverwm_utils-0.0.10.dist-info/entry_points.txt
riverwm_utils-0.0.10.dist-info/top_level.txt
riverwm_utils-0.0.10.dist-info/RECORD
