Metadata-Version: 2.1
Name: riverwm-utils
Version: 0.0.10
Summary: Utilities for the River Wayland compositor
Home-page: https://github.com/NickHastings/riverwm-utils
Author: Nick Hastings
Author-email: nicholaschastings@gmail.com
License: GPLv3
Classifier: Programming Language :: Python :: 3.7
Classifier: License :: OSI Approved :: GNU General Public License v3 (GPLv3)
Classifier: Operating System :: POSIX :: Linux
Requires-Python: >=3.7
License-File: LICENSE
Requires-Dist: pywayland (>=0.4.7)
